mannrs-2.0.0.dist-info/METADATA
mannrs-2.0.0.dist-info/WHEEL
mannrs-2.0.0.dist-info/entry_points.txt
mannrs/CLI.py
mannrs/Spectra.py
mannrs/Stencil.py
mannrs/Windfield.py
mannrs/__init__.py
mannrs/mannrs.cp313-win_amd64.pyd
mannrs/mannrs.pyi
mannrs-2.0.0.dist-info/RECORD
