Metadata-Version: 2.4
Name: mannrs
Version: 2.0.0
Requires-Dist: click>=8.0.4
Requires-Dist: netcdf4>=1.6.5
Requires-Dist: numpy>=1.21.6
Requires-Dist: pydantic>=2.5.3
Requires-Dist: scipy>=1.5.4
Requires-Dist: toml>=0.10.2
Requires-Dist: tqdm>=4.64.1
Requires-Dist: rich>=13.8.1
Summary: A Mann turbulence generator for Python written in Rust
Author-email: Jaime Liew <jaimeliew1@gmail.com>
Requires-Python: >=3.9
